LICENSE
MANIFEST.in
README.md
setup.py
wagtail_extras.egg-info/PKG-INFO
wagtail_extras.egg-info/SOURCES.txt
wagtail_extras.egg-info/dependency_links.txt
wagtail_extras.egg-info/not-zip-safe
wagtail_extras.egg-info/requires.txt
wagtail_extras.egg-info/top_level.txt
wagtailextras/__init__.py
wagtailextras/middleware.py
wagtailextras/templates/templatetags/breadcrumbs.html
wagtailextras/templates/templatetags/main_menu.html
wagtailextras/templatetags/__init__.py
wagtailextras/templatetags/wagtailextras_tags.py