Metadata-Version: 2.1
Name: wagtail-extras
Version: 0.2.8
Summary: A collection of tools one might use to make wagtail even better
Home-page: https://github.com/leukeleu/wagtail-extras
Author: Ramon de Jezus (Leukeleu)
Author-email: rdejezus@leukeleu.nl
Maintainer: Leukeleu
Maintainer-email: info@leukeleu.nl
License: MIT
Keywords: wagtail,extra
Platform: UNKNOWN
Classifier: Intended Audience :: Developers
Classifier: License :: OSI Approved :: MIT License
Classifier: Operating System :: OS Independent
Classifier: Programming Language :: Python
